ci/mac/arm64/pyproject3.12.toml
ci/mac/arm64/pyproject3.10.toml
ci/mac/arm64/pyproject3.11.toml
ci/mac/x86_64/pyproject3.12.toml
ci/mac/x86_64/pyproject3.10.toml
ci/mac/x86_64/pyproject3.11.toml
ci/linux/gpu/pyproject.toml
ci/linux/gpu/prepare_build_wheel_on_cuda.sh
braintaichi-0.0.5.dist-info/RECORD
braintaichi-0.0.5.dist-info/LICENSE
braintaichi-0.0.5.dist-info/WHEEL
braintaichi-0.0.5.dist-info/top_level.txt
braintaichi-0.0.5.dist-info/METADATA
braintaichi/__init__.py
braintaichi/cpu_ops.cpython-310-darwin.so
braintaichi/_misc.py
braintaichi/_jitconnop/csrmv.py
braintaichi/_jitconnop/__init__.py
braintaichi/_jitconnop/event_csrmv.py
braintaichi/_jitconnop/main.py
braintaichi/.dylibs/libtaichi_c_api.dylib
braintaichi/_primitive/_mlir_translation_rule.py
braintaichi/_primitive/_ad_support.py
braintaichi/_primitive/_xla_custom_op.py
braintaichi/_primitive/_batch_utils.py
braintaichi/_primitive/__init__.py
braintaichi/_eventop/csrmv.py
braintaichi/_eventop/__init__.py
braintaichi/_eventop/csrmm.py
braintaichi/_eventop/main.py
braintaichi/rand/__init__.py
braintaichi/rand/_taichi_rand.py
braintaichi/_sparseop/csrmv.py
braintaichi/_sparseop/__init__.py
braintaichi/_sparseop/utils.py
braintaichi/_sparseop/csrmm.py
braintaichi/_sparseop/main.py
braintaichi/_sparseop/coomv.py
examples/COBA_network.py
examples/COBAHH_network.py
examples/COBA_network_csr.py
examples/event_csrmv.py
benchmarks/requirements.txt
benchmarks/requirements_cuda.txt
benchmarks/README.md
benchmarks/analysis/basic/matvec/test_results/test.bat
benchmarks/analysis/basic/matvec/test_results/jitconn matvec/barchart_gpu.py
benchmarks/analysis/basic/matvec/test_results/jitconn matvec/analysis gpu.py
benchmarks/analysis/basic/matvec/test_results/jitconn matvec/jitconn_matvec_gpu.csv
benchmarks/analysis/basic/matvec/test_results/jitconn matvec/barchart_cpu.py
benchmarks/analysis/basic/matvec/test_results/jitconn matvec/jitconn_matvec_cpu.csv
benchmarks/analysis/basic/matvec/test_results/jitconn matvec/analysis cpu.py
benchmarks/analysis/basic/matvec/test_results/jitconn event matvec/jitconn_event_matvec_gpu.csv
