Metadata-Version: 2.1
Name: braintaichi
Version: 0.0.5
Summary: Leveraging Taichi Lang to customize brain dynamics operators
Home-page: https://github.com/chaobrain/braintaichi
Author: BrainTaichi Developers
Author-email: chao.brain@qq.com
License: Apache-2.0 license
Keywords: event-driven computation,sparse computation
Classifier: Natural Language :: English
Classifier: Operating System :: OS Independent
Classifier: Programming Language :: Python
Classifier: Programming Language :: Python :: 3
Classifier: Programming Language :: Python :: 3.10
Classifier: Programming Language :: Python :: 3.11
Classifier: Programming Language :: Python :: 3.12
Classifier: Intended Audience :: Science/Research
Classifier: License :: OSI Approved :: Apache Software License
Classifier: Topic :: Scientific/Engineering :: Bio-Informatics
Classifier: Topic :: Scientific/Engineering :: Mathematics
Classifier: Topic :: Scientific/Engineering :: Artificial Intelligence
Classifier: Topic :: Software Development :: Libraries
Requires-Python: >=3.10
License-File: LICENSE
Requires-Dist: brainunit
Requires-Dist: brainstate
Requires-Dist: jax
Requires-Dist: jaxlib
Requires-Dist: taichi
Provides-Extra: test
Requires-Dist: pytest; extra == "test"
